{"dependencies":[{"name":"/Users/josterman/Desktop/react/frontend/node_modules/react-router-dom/package.json","includedInParent":true,"mtime":1530221469000},{"name":"/Users/josterman/Desktop/react/frontend/package.json","includedInParent":true,"mtime":1530221544000},{"name":"/Users/josterman/Desktop/react/frontend/.babelrc","includedInParent":true,"mtime":1530221822000},{"name":"react-router/es/generatePath","loc":{"line":2,"column":25},"parent":"/Users/josterman/Desktop/react/frontend/node_modules/react-router-dom/es/generatePath.js","resolved":"/Users/josterman/Desktop/react/frontend/node_modules/react-router/es/generatePath.js"}],"generated":{"js":"\"use strict\";\n\nObject.defineProperty(exports, \"__esModule\", {\n  value: true\n});\n\nvar _generatePath = require(\"react-router/es/generatePath\");\n\nvar _generatePath2 = _interopRequireDefault(_generatePath);\n\nfunction _interopRequireDefault(obj) { return obj && obj.__esModule ? obj : { default: obj }; }\n\nexports.default = _generatePath2.default; // Written in this round about way for babel-transform-imports","map":{"mappings":[{"generated":{"line":7,"column":0},"source":"node_modules/react-router-dom/es/generatePath.js","original":{"line":2,"column":0}},{"name":"generatePath","generated":{"line":13,"column":18},"source":"node_modules/react-router-dom/es/generatePath.js","original":{"line":4,"column":15}},{"generated":{"line":13,"column":42},"source":"node_modules/react-router-dom/es/generatePath.js","original":{"line":1,"column":0}}],"sources":{"node_modules/react-router-dom/es/generatePath.js":"// Written in this round about way for babel-transform-imports\nimport generatePath from \"react-router/es/generatePath\";\n\nexport default generatePath;"},"lineCount":null}},"hash":"f2215c40fe7533774dac3c1aab60e069","cacheData":{"env":{}},"id":43}